poc_suppentest/__init__.py
poc_suppentest/__main__.py
poc_suppentest-1.0.0.dist-info/METADATA
poc_suppentest-1.0.0.dist-info/WHEEL
poc_suppentest-1.0.0.dist-info/entry_points.txt
poc_suppentest-1.0.0.dist-info/top_level.txt
poc_suppentest-1.0.0.dist-info/RECORD
