Metadata-Version: 2.1
Name: poc-suppentest
Version: 1.0.0
Summary: PoC Supply Chain Attack
Author: Security Team
Requires-Python: >=3.6
Requires-Dist: requests >=2.25.0
